topic_handler
